dictns.py
dictns-1.5.dist-info/DESCRIPTION.rst
dictns-1.5.dist-info/METADATA
dictns-1.5.dist-info/RECORD
dictns-1.5.dist-info/WHEEL
dictns-1.5.dist-info/metadata.json
dictns-1.5.dist-info/top_level.txt
