Metadata-Version: 2.0
Name: dictns
Version: 1.5
Summary: simple class that merge dictionary and object API
Home-page: http://github.com/tardyp/dictns
Author: Pierre Tardy
Author-email: tardyp@gmail.com
License: BSD
Download-URL: http://github.com/tardyp/dictns
Keywords: dict,object
Platform: Any
Classifier: License :: OSI Approved :: BSD License
Classifier: Programming Language :: Python
Classifier: Topic :: Software Development :: Libraries :: Python Modules
Classifier: Intended Audience :: Developers
